[{"chinese":"yóujú","english":"post office","categories":["noun","place","building"]},{"chinese":"wǎng","english":"to go toward, to","categories":["co verb","direction"]},{"chinese":"yìzhí","english":"straight, constantly","categories":["adverb","direction"]},{"chinese":"dì","english":"prefix for numbers","categories":["pronoun","numbers"]},{"chinese":"shízìlùkǒu","english":"intersection","categories":["noun","direction","building"]},{"chinese":"lùkǒu","english":"street entrance","categories":["direction","noun","building"]},{"chinese":"yòu","english":"right","categories":["noun","direction"]},{"chinese":"zhuǎn","english":"to turn","categories":["verb","direction"]},{"chinese":"jīngguò","english":"to pass by, to pass through","categories":["verb","direction"]},{"chinese":"bǎihuògōngsī","english":"department store","categories":["noun","building"]},{"chinese":"jiā","english":"measure word building","categories":["measure word","building"]},{"chinese":"zài","english":"then","categories":["adverb","talk"]},{"chinese":"yàoshì","english":"if","categories":["movable verb","talk"]},{"chinese":"bāng","english":"to help","categories":["verb"]},{"chinese":"bāngmáng","english":"to help someone","categories":["verb object",""]},{"chinese":"chéngshì","english":"city","categories":["noun","place","direction","building"]},{"chinese":"xībù","english":"western part","categories":["noun","direction","place"]},{"chinese":"xī","english":"west","categories":["noun","coordinate","direction","place"]},{"chinese":"bù","english":"part,area","categories":["place","direction"]},{"chinese":"dōngbù","english":"eastern part","categories":["noun","direction","place"]},{"chinese":"dōngbù","english":"east","categories":["noun","coordinate"]},{"chinese":"běi","english":"north","categories":["noun","coordinate"]},{"chinese":"ránhòu","english":"then","categories":["conjuction","talk"]},{"chinese":"xiān","english":"first, before, in advance","categories":["adverb","talk"]},{"chinese":"líkāi","english":"to leave","categories":["verb"]},{"chinese":"qǐfēi","english":"to take off","categories":["verb"]},{"chinese":"búkèqi","english":"you are welcome","categories":["expression","talk"]},{"chinese":"kèqi","english":"to be polite","categories":["stative verb"]},{"chinese":"nán","english":"south","categories":["coordinate","direction","noun"]},{"chinese":"hǎi","english":"ocean, sea","categories":["noun","nature","place"]},{"chinese":"gāo","english":"to be tall","categories":["stative verb","body","fisical condition"]},{"chinese":"hé","english":"river","categories":["noun","nature","place"]},{"chinese":"tiáo","english":"measure word for narrow things","categories":["measure word","direction"]},{"chinese":"zuǒ","english":"left","categories":["noun","direction"]},{"chinese":"jiē","english":"street","categories":["noun","place","direction"]},{"chinese":"ba","english":"sentence suffix, indicate request or suggestion","categories":["expression","talk"]},{"chinese":"","categories":[]},{"chinese":"","categories":[]},{"chinese":" ","categories":[]}]